ttws/__init__.py
ttws/cli.py
ttws-0.8.4.dist-info/METADATA
ttws-0.8.4.dist-info/WHEEL
ttws-0.8.4.dist-info/entry_points.txt
ttws-0.8.4.dist-info/top_level.txt
ttws-0.8.4.dist-info/RECORD
