Metadata-Version: 2.1
Name: ttws
Version: 0.8.4
Summary: Script to remove trailing whitespaces from textfiles and more.
Home-page: https://github.com/simulatino/trimtrailingwhitespaces
Author: Dietmar Winkler
Author-email: dietmar.winkler@dwe.no
License: UNLICENSE
Platform: Posix; MacOS X; Windows
Classifier: Environment :: Console
Classifier: Intended Audience :: Developers
Classifier: Operating System :: OS Independent
Classifier: Programming Language :: Python :: 2
Classifier: Programming Language :: Python :: 3
Requires-Dist: pyparsing
Requires-Dist: python-magic
Provides-Extra: testing
Requires-Dist: pytest ; extra == 'testing'
